LICENSE
MANIFEST.in
README.rst
setup.py
django_offermaker.egg-info/PKG-INFO
django_offermaker.egg-info/SOURCES.txt
django_offermaker.egg-info/dependency_links.txt
django_offermaker.egg-info/not-zip-safe
django_offermaker.egg-info/requires.txt
django_offermaker.egg-info/top_level.txt
offermaker/__init__.py
offermaker/core.py
offermaker/models.py
offermaker/tests.py
offermaker/views.py
offermaker/static/offermaker/bootstrap-tokenfield.min.css
offermaker/static/offermaker/bootstrap-tokenfield.min.js
offermaker/static/offermaker/editor.css
offermaker/static/offermaker/editor.js
offermaker/static/offermaker/jquery-ui.min.css
offermaker/static/offermaker/jquery-ui.min.js
offermaker/static/offermaker/offermaker.css
offermaker/static/offermaker/offermaker.js
offermaker/static/offermaker/sprintf.min.js
offermaker/static/offermaker/images/icon_error.gif
offermaker/static/offermaker/images/ui-bg_flat_0_aaaaaa_40x100.png
offermaker/static/offermaker/images/ui-bg_flat_75_ffffff_40x100.png
offermaker/static/offermaker/images/ui-bg_glass_55_fbf9ee_1x400.png
offermaker/static/offermaker/images/ui-bg_glass_65_ffffff_1x400.png
offermaker/static/offermaker/images/ui-bg_glass_75_dadada_1x400.png
offermaker/static/offermaker/images/ui-bg_glass_75_e6e6e6_1x400.png
offermaker/static/offermaker/images/ui-bg_glass_95_fef1ec_1x400.png
offermaker/static/offermaker/images/ui-bg_highlight-soft_75_cccccc_1x100.png
offermaker/static/offermaker/images/ui-icons_222222_256x240.png
offermaker/static/offermaker/images/ui-icons_2e83ff_256x240.png
offermaker/static/offermaker/images/ui-icons_454545_256x240 (1).png
offermaker/static/offermaker/images/ui-icons_454545_256x240.png
offermaker/static/offermaker/images/ui-icons_888888_256x240.png
offermaker/static/offermaker/images/ui-icons_cd0a0a_256x240.png
offermaker/templatetags/__init__.py
offermaker/templatetags/offermaker.py
offermaker/tests2/__init__.py
offermaker/tests2/_functional.py
offermaker/tests2/_input.py
offermaker/tests2/_math.py
offermaker/tests2/_offermaker.py
offermaker/tests2/_restrictionset.py
offermaker/tests2/_views.py
offermaker/tests2/admin.py
offermaker/tests2/models.py
offermaker/tests2/urls.py
offermaker/tests2/views.py