Metadata-Version: 1.1
Name: django-offermaker
Version: 0.9.8
Summary: Django application that allows creation, preview and usage of custom multivariant restrictions applied on the forms.
Home-page: http://offermaker.kjw.pt
Author: Kamil Kujawinski
Author-email: kamil@kujawinski.net
License: LGPL
Platform: UNKNOWN
Classifier: Environment :: Web Environment
Classifier: Framework :: Django
Classifier: Intended Audience :: Developers
Classifier: License :: OSI Approved :: GNU Lesser General Public License v3 or later (LGPLv3+)
Classifier: Operating System :: OS Independent
Classifier: Programming Language :: Python
Classifier: Programming Language :: Python :: 2.6
Classifier: Programming Language :: Python :: 2.7
Classifier: Topic :: Internet :: WWW/HTTP
Classifier: Topic :: Internet :: WWW/HTTP :: Dynamic Content
